<PAMDataset>
  <PAMRasterBand band="1">
    <Histograms>
      <HistItem>
        <HistMin>-0.9805385131835938</HistMin>
        <HistMax>1962.057564880371</HistMax>
        <BucketCount>1000</BucketCount>
        <IncludeOutOfRange>0</IncludeOutOfRange>
        <Approximate>0</Approximate>
        <HistCounts>18085|160|153|332|64|171|38|28|67|31|102|22|27|30|25|51|12|13|19|11|24|13|7|13|10|31|5|7|6|11|6|11|10|14|2|2|14|8|1|7|5|8|6|1|3|2|4|7|3|3|4|3|2|2|4|1|2|2|3|3|2|2|3|2|1|5|3|3|1|4|0|3|6|2|6|0|2|3|1|2|1|1|1|2|1|1|5|0|5|0|1|0|0|2|3|1|2|1|0|3|0|3|2|2|0|0|3|1|2|0|0|0|3|0|2|0|0|0|1|3|2|0|0|0|0|0|2|3|1|0|1|0|1|0|1|3|0|0|2|0|0|0|1|0|0|1|0|0|0|0|0|0|1|0|1|0|2|0|0|0|0|0|0|0|0|1|0|0|1|0|0|0|0|0|0|0|0|0|0|1|0|0|1|0|0|0|0|0|0|0|0|0|0|0|0|1|0|0|0|0|0|0|0|0|1|0|0|0|0|1|0|0|1|0|0|1|0|0|0|0|0|1|0|0|0|1|0|0|0|0|0|1|0|0|0|0|1|1|0|0|0|0|0|1|0|2|0|0|1|0|0|1|0|0|0|0|0|0|0|0|0|0|0|0|0|0|0|0|0|0|0|0|1|0|0|0|0|0|0|3|0|0|0|0|0|0|0|1|0|0|0|0|1|0|0|0|0|0|0|0|1|0|0|1|0|1|0|0|0|0|0|0|0|0|0|0|0|0|0|0|0|0|0|0|0|0|0|0|0|0|0|0|0|0|0|0|0|0|0|0|0|0|0|0|0|0|0|0|0|0|0|1|0|0|0|1|0|0|0|0|0|0|0|0|0|0|0|0|0|0|1|0|0|0|0|0|1|0|0|0|0|0|0|0|0|0|0|0|0|0|0|0|0|0|0|0|0|0|0|0|0|0|0|0|0|0|0|0|0|0|0|1|0|0|0|0|0|0|0|0|0|0|0|0|0|0|0|0|0|0|0|0|0|0|0|0|0|0|0|0|0|0|0|0|0|0|0|0|0|0|0|0|0|0|0|0|0|0|0|1|0|0|0|0|0|0|1|0|0|0|0|0|0|0|0|0|0|0|0|0|0|0|0|1|0|0|0|1|0|0|0|0|0|0|0|0|0|0|0|0|0|0|0|0|0|0|0|0|0|0|0|0|0|0|0|0|0|0|0|0|0|0|0|0|0|0|0|0|0|0|0|0|0|0|0|0|0|0|0|0|0|0|0|0|0|0|0|0|0|0|0|0|0|0|0|0|0|0|0|0|0|0|0|0|0|0|0|0|0|0|0|0|0|0|0|0|0|0|0|0|0|0|1|0|0|0|0|0|0|0|0|0|0|0|0|0|0|0|0|0|0|0|0|0|0|0|0|0|0|0|0|0|0|0|0|0|0|0|0|0|0|0|0|0|0|0|0|0|0|0|0|0|0|0|0|0|0|0|0|0|0|0|0|0|0|0|0|0|0|0|0|0|0|0|0|0|0|0|0|0|0|0|0|0|1|0|0|1|0|0|0|0|0|0|0|0|0|0|0|0|0|0|0|0|0|1|0|0|0|0|0|0|0|0|0|0|0|0|0|0|0|0|0|0|0|0|0|0|0|0|0|0|0|0|0|0|0|0|0|0|0|0|0|0|0|0|0|0|0|0|0|0|0|0|0|0|0|0|0|0|0|0|0|0|0|0|0|0|0|0|0|0|0|1|0|0|0|0|0|0|0|0|0|0|0|0|0|0|0|0|0|0|0|0|0|0|0|0|0|0|0|0|0|0|0|0|0|0|0|0|0|0|0|0|0|0|0|0|0|0|0|0|0|0|1|0|0|0|0|0|0|0|0|0|0|0|0|0|0|0|0|0|0|0|0|0|0|0|0|0|0|0|0|0|0|0|0|0|0|0|0|0|0|0|0|0|0|0|0|0|0|0|0|0|0|0|0|0|0|0|0|0|0|0|0|0|0|0|0|0|0|0|0|0|0|0|0|0|0|0|0|0|0|0|0|0|0|0|0|0|0|0|0|0|0|0|0|0|0|0|0|0|0|0|0|0|0|0|0|0|0|0|0|0|0|0|0|0|0|0|0|0|0|0|0|0|0|0|0|0|0|0|0|0|0|0|0|0|0|0|0|0|0|0|0|0|0|0|0|0|0|0|0|0|0|0|0|0|0|0|0|0|0|0|0|0|0|0|0|0|0|0|0|0|0|0|0|0|0|0|0|0|0|0|0|0|0|0|0|0|0|0|0|0|0|0|0|0|0|1</HistCounts>
      </HistItem>
    </Histograms>
    <Metadata>
      <MDI key="STATISTICS_MAXIMUM">1961.0770263672</MDI>
      <MDI key="STATISTICS_MEAN">4.32828137606</MDI>
      <MDI key="STATISTICS_MINIMUM">0</MDI>
      <MDI key="STATISTICS_STDDEV">40.852161174863</MDI>
    </Metadata>
  </PAMRasterBand>
</PAMDataset>
